inmation_api_client/__init__.py
inmation_api_client/data.py
inmation_api_client/error.py
inmation_api_client/inclient.py
inmation_api_client/model.py
inmation_api_client/options.py
inmation_api_client/wsclient.py
inmation_api_client/eventemitter/__init__.py
inmation_api_client/eventemitter/emitter.py
inmation_api_client/eventemitter/iterable.py
inmation_api_client/eventemitter/test_emitter.py
inmation_api_client/eventemitter/test_iterable.py
inmation_api_client/examples/__init__.py
inmation_api_client/examples/read_write.py
inmation_api_client/examples/readrawhistoricaldata.py
inmation_api_client/examples/subscribe_ondatachanged.py
inmation_api_client/tests/__init__.py
inmation_api_client/tests/test.py
inmation_api_client/tests/integration/__init__.py
inmation_api_client/tests/integration/connect_test.py
inmation_api_client/tests/integration/environment.py
inmation_api_client/tests/integration/execfunction_readhist_test.py
inmation_api_client/tests/integration/execfunction_test.py
inmation_api_client/tests/integration/main.py
inmation_api_client/tests/integration/read_test.py
inmation_api_client/tests/integration/readhistoricaldata_test.py
inmation_api_client/tests/integration/runscript_test.py
inmation_api_client/tests/integration/subscribe_test.py
inmation_api_client/tests/integration/write_test.py
inmation_api_client-0.2.1.dist-info/METADATA
inmation_api_client-0.2.1.dist-info/RECORD
inmation_api_client-0.2.1.dist-info/WHEEL
inmation_api_client-0.2.1.dist-info/top_level.txt
