Metadata-Version: 2.1
Name: inmation-api-client
Version: 0.2.1
Summary: API client for system:inmation.
Home-page: https://inmation.com
Author: Alexandr Sapunji
Author-email: alexandr.sapunji@inmation.com
License: MIT
Platform: UNKNOWN
Classifier: Development Status :: 3 - Alpha
Classifier: Programming Language :: Python :: 3.6
Classifier: Operating System :: OS Independent
Requires-Dist: websockets (==5.0)
